{
  "items": [
    {
      "comment": "(log) batch-id: 8ab653ce-1eb6-4e61-af23-5eb037d6f656\nArtifactId: greece\nBuild-Timestamp: 20210809085400\nGit-Branch: develop\nGit-Origin: https://github.com/yupiik/batch-sample-data.git\nGit-Sha: 221b42b17fea715719eb0517971b23dd6528069a\nGit-Time: 2021-08-09T07:19:48Z\nGroupId: com.yupiik.batch\nVersion: 1.0.2-SNAPSHOT\n",
      "finished": "2021-08-09T10:00:46.859726Z",
      "id": "e9fa7f66-0809-44a6-9fe1-fc6bc08141ba",
      "name": "Greece",
      "started": "2021-08-09T10:00:25.338185Z",
      "status": "SUCCESS"
    },
    {
      "comment": "(log) batch-id: be885c71-114d-47b9-800f-5ed66fed0938\nArtifactId: liechtenstein\nBuild-Timestamp: 20210809085400\nGit-Branch: develop\nGit-Origin: https://github.com/yupiik/batch-sample-data.git\nGit-Sha: 221b42b17fea715719eb0517971b23dd6528069a\nGit-Time: 2021-08-09T07:19:48Z\nGroupId: com.yupiik.batch\nVersion: 1.0.2-SNAPSHOT\n",
      "finished": "2021-08-09T10:00:46.526175Z",
      "id": "1c5ad662-bd0e-454f-9367-4d8c98ff14cf",
      "name": "Liechtenstein",
      "started": "2021-08-09T10:00:30.583686Z",
      "status": "SUCCESS"
    },
    {
      "comment": "(log) batch-id: d858577d-2f2a-4106-ba29-5bcbfb918e36\nArtifactId: bulgaria\nBuild-Timestamp: 20210809085400\nGit-Branch: develop\nGit-Origin: https://github.com/yupiik/batch-sample-data.git\nGit-Sha: 221b42b17fea715719eb0517971b23dd6528069a\nGit-Time: 2021-08-09T07:19:48Z\nGroupId: com.yupiik.batch\nVersion: 1.0.2-SNAPSHOT\n",
      "finished": "2021-08-09T10:00:44.236641Z",
      "id": "89a26dd0-e259-4395-b668-c4d6d8c270cb",
      "name": "Bulgaria",
      "started": "2021-08-09T10:00:19.422299Z",
      "status": "SUCCESS"
    },
    {
      "comment": "(log) batch-id: e296d563-0fa5-4bc5-9920-d541a1cbf927\nArtifactId: luxembourg\nBuild-Timestamp: 20210809085400\nGit-Branch: develop\nGit-Origin: https://github.com/yupiik/batch-sample-data.git\nGit-Sha: 221b42b17fea715719eb0517971b23dd6528069a\nGit-Time: 2021-08-09T07:19:48Z\nGroupId: com.yupiik.batch\nVersion: 1.0.2-SNAPSHOT\n",
      "finished": "2021-08-09T10:00:43.486399Z",
      "id": "5e4a6156-ad3c-4007-af9c-d993fc5b52c0",
      "name": "Luxembourg",
      "started": "2021-08-09T10:00:26.200257Z",
      "status": "SUCCESS"
    },
    {
      "comment": "(log) batch-id: 03644e70-f2cc-4585-af5d-679459f62ddc\nArtifactId: romania\nBuild-Timestamp: 20210809085400\nGit-Branch: develop\nGit-Origin: https://github.com/yupiik/batch-sample-data.git\nGit-Sha: 221b42b17fea715719eb0517971b23dd6528069a\nGit-Time: 2021-08-09T07:19:48Z\nGroupId: com.yupiik.batch\nVersion: 1.0.2-SNAPSHOT\n",
      "finished": "2021-08-09T10:00:43.094181Z",
      "id": "f464af54-31b6-4eda-9138-2e21d62ad250",
      "name": "Romania",
      "started": "2021-08-09T10:00:29.105124Z",
      "status": "SUCCESS"
    },
    {
      "comment": "(log) batch-id: 5715ffb1-1ebf-4171-871a-b915d6fca230\nArtifactId: netherlands\nBuild-Timestamp: 20210809085400\nGit-Branch: develop\nGit-Origin: https://github.com/yupiik/batch-sample-data.git\nGit-Sha: 221b42b17fea715719eb0517971b23dd6528069a\nGit-Time: 2021-08-09T07:19:48Z\nGroupId: com.yupiik.batch\nVersion: 1.0.2-SNAPSHOT\n",
      "finished": "2021-08-09T10:00:42.337573Z",
      "id": "919e4275-0c3c-481e-b2b6-d6f5e6420838",
      "name": "Netherlands",
      "started": "2021-08-09T10:00:22.573371Z",
      "status": "SUCCESS"
    },
    {
      "comment": "(log) batch-id: fee3c52e-6525-47a1-be34-5afc4a89a17c\nArtifactId: czech-republic\nBuild-Timestamp: 20210809085400\nGit-Branch: develop\nGit-Origin: https://github.com/yupiik/batch-sample-data.git\nGit-Sha: 221b42b17fea715719eb0517971b23dd6528069a\nGit-Time: 2021-08-09T07:19:48Z\nGroupId: com.yupiik.batch\nVersion: 1.0.2-SNAPSHOT\n",
      "finished": "2021-08-09T10:00:42.126930Z",
      "id": "97d50616-07a3-4349-8940-2ab1477ca407",
      "name": "CzechRepublic",
      "started": "2021-08-09T10:00:13.486585Z",
      "status": "SUCCESS"
    },
    {
      "comment": "(log) batch-id: 606d4d72-299a-4258-b1a8-9dd09c730d97\nArtifactId: slovakia\nBuild-Timestamp: 20210809085400\nGit-Branch: develop\nGit-Origin: https://github.com/yupiik/batch-sample-data.git\nGit-Sha: 221b42b17fea715719eb0517971b23dd6528069a\nGit-Time: 2021-08-09T07:19:48Z\nGroupId: com.yupiik.batch\nVersion: 1.0.2-SNAPSHOT\n",
      "finished": "2021-08-09T10:00:41.965496Z",
      "id": "c2ab271f-83ad-4501-923c-66ca50dc2489",
      "name": "Slovakia",
      "started": "2021-08-09T10:00:25.172458Z",
      "status": "SUCCESS"
    },
    {
      "comment": "(log) batch-id: a57690ec-1076-40db-9c34-3959848d3d4c\nArtifactId: iceland\nBuild-Timestamp: 20210809085400\nGit-Branch: develop\nGit-Origin: https://github.com/yupiik/batch-sample-data.git\nGit-Sha: 221b42b17fea715719eb0517971b23dd6528069a\nGit-Time: 2021-08-09T07:19:48Z\nGroupId: com.yupiik.batch\nVersion: 1.0.2-SNAPSHOT\n",
      "finished": "2021-08-09T10:00:41.410192Z",
      "id": "793d5320-856a-4a6a-91d5-84a4a3bb8846",
      "name": "Iceland",
      "started": "2021-08-09T10:00:28.860647Z",
      "status": "SUCCESS"
    },
    {
      "comment": "(log) batch-id: b7bab69a-70b8-4995-8188-26cf36c79ab4\nArtifactId: estonia\nBuild-Timestamp: 20210809085400\nGit-Branch: develop\nGit-Origin: https://github.com/yupiik/batch-sample-data.git\nGit-Sha: 221b42b17fea715719eb0517971b23dd6528069a\nGit-Time: 2021-08-09T07:19:48Z\nGroupId: com.yupiik.batch\nVersion: 1.0.2-SNAPSHOT\n",
      "finished": "2021-08-09T10:00:34.648069Z",
      "id": "7262f6c7-b522-4e6d-930b-4f4c145191ff",
      "name": "Estonia",
      "started": "2021-08-09T10:00:14.873363Z",
      "status": "SUCCESS"
    }
  ],
  "total": 19519
}
